vtfwriter-stubs/__init__.pyi
vtfwriter_stubs-1.1.0.dist-info/METADATA
vtfwriter_stubs-1.1.0.dist-info/WHEEL
vtfwriter_stubs-1.1.0.dist-info/RECORD
