Metadata-Version: 2.1
Name: vtfwriter-stubs
Version: 1.1.0
Summary: Type stubs for the Python interface to libVTFExpressAPI
Author-Email: Eivind Fonn <eivind.fonn@sintef.no>
License: GPL3-or-later
Requires-Python: <4.0,>=3.9
Requires-Dist: typing-extensions>=4.9.0
